<lcgdict>
  <class name="PositionSoA" />
  <class name="AlgebraSoA" />
  <class name="CombinedPhysicsObject"/>
  <class name="NGTSoA"/>
  <class name="PositionSoACollection"/>
  <class name="AlgebraSoACollection"/>
  <class name="CombinedPhysicsObjectCollection"/>
  <class name="NGTSoAHostCollection" />
  <class name="edm::Wrapper<PositionSoACollection>"/>
  <class name="edm::Wrapper<AlgebraSoACollection>"/>
  <class name="edm::Wrapper<CombinedPhysicsObjectCollection>"/>
  <class name="edm::Wrapper<NGTSoAHostCollection>"/>
</lcgdict>
